README.md
setup.py
ssml_builder/__init__.py
ssml_builder/core.py
ssml_builder.egg-info/PKG-INFO
ssml_builder.egg-info/SOURCES.txt
ssml_builder.egg-info/dependency_links.txt
ssml_builder.egg-info/top_level.txt