Metadata-Version: 1.0
Name: ssml-builder
Version: 1.0.7
Summary: SSML Builder for Alexa Skill Development in Python
Home-page: https://github.com/Reverseblade/ssml-builder
Author: Yuta Fujisawa
Author-email: UNKNOWN
License: Free
Platform: UNKNOWN
